dtamg_py/__init__.py
dtamg_py/build_datapackage.py
dtamg_py/build_datapackages.py
dtamg_py/build_documentation_folder.py
dtamg_py/cli.py
dtamg_py/compare_resource_paths.py
dtamg_py/convert_to_csv.py
dtamg_py/create.py
dtamg_py/extract.py
dtamg_py/full_extract.py
dtamg_py/remove_sqs.py
dtamg_py/update.py
dtamg_py/utils.py
dtamg_py/validate.py
dtamg_py/validate_tableschemas.py
dtamg_py-0.1.6.dist-info/LICENCE.txt
dtamg_py-0.1.6.dist-info/METADATA
dtamg_py-0.1.6.dist-info/WHEEL
dtamg_py-0.1.6.dist-info/entry_points.txt
dtamg_py-0.1.6.dist-info/top_level.txt
dtamg_py-0.1.6.dist-info/RECORD
