Metadata-Version: 2.1
Name: dtamg-py
Version: 0.1.6
Summary: Gestão do processos internos da Diretoria Central de Transparência Ativa
Home-page: https://github.com/gabrielbdornas/meu-contracheque
Author: CONTROLADORIA GERAL DO ESTADO DE MINAS GERAIS - CGE/MG
Author-email: dadosabertos@cge.mg.gov.br
License: UNKNOWN
Keywords: python,Minas Gerais,Contracheque
Platform: UNKNOWN
Classifier: Development Status :: 1 - Planning
Classifier: Intended Audience :: Developers
Classifier: Programming Language :: Python :: 3
Classifier: Operating System :: Unix
Classifier: Operating System :: MacOS :: MacOS X
Classifier: Operating System :: Microsoft :: Windows
Requires-Dist: PyMySQL (>=1.0.2)
Requires-Dist: ckanapi (>=4.0.0)
Requires-Dist: click (>=8.0.1)
Requires-Dist: dpckan (>=0.1.11)
Requires-Dist: frictionless-ckan-mapper (>=1.0.6)
Requires-Dist: frictionless (>=4.16.6)
Requires-Dist: jsonpatch (>=1.32)
Requires-Dist: openpyxl (==3.0.9)
Requires-Dist: pandas (==1.4.1)
Requires-Dist: psycopg2 (>=2.9.1)
Requires-Dist: python-dotenv (>=0.19.1)
Requires-Dist: ruamel.yaml (==0.17.17)
Requires-Dist: xlrd (>=1.0.0)
